cardsol/__init__.py
cardsol/problem/__init__.py
cardsol/problem/abstract_classes.py
cardsol/problem/constraints.py
cardsol/problem/functions.py
cardsol/problem/model.py
cardsol/problem/objective.py
cardsol/problem/variables.py
cardsol/solver/__init__.py
cardsol/solver/abstract_solver.py
cardsol/solver/outer_lpnlp/__init__.py
cardsol/solver/outer_lpnlp/master.py
cardsol/solver/outer_lpnlp/primal.py
cardsol/solver/outer_lpnlp/solver.py
cardsol/solver/subsolvers/__init__.py
cardsol/solver/subsolvers/gurobiOA.py
cardsol/solver/subsolvers/gurobi_qp.py
cardsol/solver/subsolvers/gurobilpnlp.py
cardsol-0.1.2.dist-info/METADATA
cardsol-0.1.2.dist-info/WHEEL
cardsol-0.1.2.dist-info/top_level.txt
cardsol-0.1.2.dist-info/RECORD
