Metadata-Version: 2.1
Name: cardsol
Version: 0.1.2
Summary: Cardinality constrained Solver
Home-page: https://github.com/Alirezalm/cardsol.git
Author: Alireza Olama
Author-email: alireza.lm69@gmail.com
License: MIT
Platform: UNKNOWN
Classifier: License :: OSI Approved :: MIT License
Classifier: Programming Language :: Python :: 3
Classifier: Programming Language :: Python :: 3.8
Requires-Dist: numpy
Requires-Dist: scipy
Requires-Dist: gurobipy
